latext/__init__.py
latext/latext.py
latext-0.0.6.dist-info/DESCRIPTION.rst
latext-0.0.6.dist-info/METADATA
latext-0.0.6.dist-info/RECORD
latext-0.0.6.dist-info/WHEEL
latext-0.0.6.dist-info/metadata.json
latext-0.0.6.dist-info/top_level.txt
