Metadata-Version: 2.0
Name: latext
Version: 0.0.6
Summary: For converting LaTeX to spoken text.
Home-page: https://github.com/Alex-Tremayne/LaTeXt
Author: Alex Tremayne
Author-email: alexjtremayne@gmail.com
License: MIT
Platform: UNKNOWN
Classifier: Development Status :: 3 - Alpha
Classifier: License :: OSI Approved :: MIT License
Classifier: Programming Language :: Python :: 3.6
